county_property_data.py
county_property_data-0.1.dist-info/METADATA
county_property_data-0.1.dist-info/WHEEL
county_property_data-0.1.dist-info/top_level.txt
county_property_data-0.1.dist-info/RECORD
