Metadata-Version: 2.1
Name: county-property-data
Version: 0.1
Summary: A Python module for collecting property data by county.
Author: Philip Diegel
Requires-Dist: requests
Requires-Dist: beautifulsoup4
